akamai_edgeauth-0.3.1-py2.7-nspkg.pth
akamai/authtoken/__init__.py
akamai/authtoken/authtoken.py
akamai/edgeauth/__init__.py
akamai/edgeauth/edgeauth.py
akamai_edgeauth-0.3.1.dist-info/METADATA
akamai_edgeauth-0.3.1.dist-info/RECORD
akamai_edgeauth-0.3.1.dist-info/WHEEL
akamai_edgeauth-0.3.1.dist-info/namespace_packages.txt
akamai_edgeauth-0.3.1.dist-info/top_level.txt
