Metadata-Version: 2.1
Name: akamai-edgeauth
Version: 0.3.1
Summary: Akamai Edge Authorization Token for Property Manager Behavior
Home-page: https://github.com/akamai/EdgeAuth-Token-Python
Author: Astin Choi
Author-email: asciineo@gmail.com
License: Apache 2.0
Keywords: edgeauth auth token akamai openapi open api
Platform: UNKNOWN
Classifier: Intended Audience :: Developers
Classifier: Programming Language :: Python
Classifier: Programming Language :: Python :: 2.6
Classifier: Programming Language :: Python :: 2.7
Classifier: Programming Language :: Python :: 3
Classifier: Programming Language :: Python :: 3.3
Classifier: Programming Language :: Python :: 3.4
Classifier: Programming Language :: Python :: 3.5
Classifier: Programming Language :: Python :: 3.6
Classifier: Programming Language :: Python :: Implementation :: CPython
Classifier: Programming Language :: Python :: Implementation :: PyPy
